__init__.py
airscrapy.py
airscrapy-1.0.0.dist-info/LICENCE
airscrapy-1.0.0.dist-info/METADATA
airscrapy-1.0.0.dist-info/WHEEL
airscrapy-1.0.0.dist-info/top_level.txt
airscrapy-1.0.0.dist-info/RECORD
