Metadata-Version: 2.1
Name: airscrapy
Version: 1.0.0
Summary: Scrapy contrib for Airflow
Author: Fabien Vauchelles
Project-URL: Homepage, https://github.com/scrapoxy/airscrapy
Project-URL: Issues, https://github.com/scrapoxy/airscrapy/issues
Classifier: Programming Language :: Python :: 3
Classifier: License :: OSI Approved :: MIT License
Classifier: Operating System :: OS Independent
Requires-Python: >=3.8
License-File: LICENCE
Requires-Dist: scrapy
